mocksftp/__init__.py
mocksftp/decorators.py
mocksftp/interface.py
mocksftp/keys.py
mocksftp/pytest_plugin.py
mocksftp/server.py
mocksftp/keys/sample-user-key
mocksftp/keys/sample-user-key.pub
mocksftp/keys/server-key
mocksftp/keys/server-key.pub
mocksftp-1.0.1.dist-info/DESCRIPTION.rst
mocksftp-1.0.1.dist-info/METADATA
mocksftp-1.0.1.dist-info/RECORD
mocksftp-1.0.1.dist-info/WHEEL
mocksftp-1.0.1.dist-info/entry_points.txt
mocksftp-1.0.1.dist-info/metadata.json
mocksftp-1.0.1.dist-info/top_level.txt
