Metadata-Version: 2.0
Name: mocksftp
Version: 1.0.1
Summary: Mock SFTP server for testing purposes
Home-page: https://github.com/LabD/python-mocksftp
Author: Michael van Tellingen
Author-email: michaelvantellingen@gmail.com
License: MIT
Platform: UNKNOWN
Classifier: Intended Audience :: Developers
Classifier: License :: OSI Approved :: MIT License
Requires-Dist: paramiko
Provides-Extra: test
Requires-Dist: pretend (==1.0.8); extra == 'test'
Requires-Dist: pytest-cov (==2.4.0); extra == 'test'
Requires-Dist: pytest (==3.0.6); extra == 'test'
Requires-Dist: isort (==4.2.5); extra == 'test'
Requires-Dist: flake8 (==3.2.1); extra == 'test'
Requires-Dist: flake8-blind-except (==0.1.1); extra == 'test'
Requires-Dist: flake8-debugger (==1.4.0); extra == 'test'
